Metadata-Version: 2.1
Name: passbolted
Version: 0.2
Summary: Password Reader by name using py-passbolt
Author: Shamail Tayyab
Author-email: tayyab.shamail@gmail.com
Classifier: Programming Language :: Python :: 3
Classifier: License :: OSI Approved :: MIT License
Classifier: Operating System :: OS Independent
Requires-Dist: toml
Requires-Dist: py-passbolt
